flask_navigation/__init__.py
flask_navigation/api.py
flask_navigation/item.py
flask_navigation/navbar.py
flask_navigation/signals.py
flask_navigation/utils.py
tests/integration/__init__.py
tests/integration/app.py
tests/integration/ext.py
tests/integration/test_app.py
tests/integration/views.py
flask_navigation_temp_python_311-0.2.1.dist-info/LICENSE
flask_navigation_temp_python_311-0.2.1.dist-info/METADATA
flask_navigation_temp_python_311-0.2.1.dist-info/WHEEL
flask_navigation_temp_python_311-0.2.1.dist-info/top_level.txt
flask_navigation_temp_python_311-0.2.1.dist-info/RECORD
