Metadata-Version: 2.1
Name: flask-navigation-temp-python-311
Version: 0.2.1
Summary: The navigation of Flask application.
Home-page: https://github.com/etalab/flask-navigation-temp-python-311
Author: Jiangge Zhang
Author-email: tonyseek@gmail.com
License: MIT
Keywords: navigation,flask,navbar,nav
Classifier: Programming Language :: Python
Classifier: Programming Language :: Python :: 2.7
Classifier: Programming Language :: Python :: 3.3
Classifier: Programming Language :: Python :: 3.4
Classifier: Programming Language :: Python :: Implementation :: PyPy
Classifier: Development Status :: 3 - Alpha
Classifier: License :: OSI Approved :: MIT License
Classifier: Intended Audience :: Developers
Classifier: Operating System :: OS Independent
Classifier: Environment :: Web Environment
Classifier: Framework :: Flask
Classifier: Topic :: Software Development :: Libraries :: Python Modules
License-File: LICENSE
Requires-Dist: Flask
Requires-Dist: blinker
